{
    "expand": "html",
    "self": "http:\/\/fw02.zend.com\/issues\/rest\/api\/latest\/issue\/ZF-11889",
    "key": "ZF-11889",
    "fields": {
        "summary": {
            "name": "summary",
            "type": "java.lang.String",
            "value": "Zend_Cloud_StorageService_Adapter_S3::listItems() only returns maximum of 1000 filepaths (in wrong format)"
        },
        "timetracking": {
            "name": "timetracking",
            "type": "com.atlassian.jira.issue.fields.TimeTrackingSystemField"
        },
        "issuetype": {
            "name": "issuetype",
            "type": "com.atlassian.jira.issue.issuetype.IssueType",
            "value": {
                "self": "http:\/\/fw02.zend.com\/issues\/rest\/api\/latest\/issueType\/1",
                "name": "Bug",
                "subtask": false
            }
        },
        "votes": {
            "name": "votes",
            "type": "com.atlassian.jira.issue.fields.VotesSystemField",
            "value": {
                "self": "http:\/\/fw02.zend.com\/issues\/rest\/api\/latest\/issue\/ZF-11889\/votes",
                "votes": 0,
                "hasVoted": false
            }
        },
        "security": {
            "name": "security",
            "type": "com.atlassian.jira.issue.security.IssueSecurityLevel"
        },
        "fixVersions": {
            "name": "fixVersions",
            "type": "com.atlassian.jira.project.version.Version",
            "value": [

            ]
        },
        "reporter": {
            "name": "reporter",
            "type": "com.opensymphony.user.User",
            "value": {
                "self": "http:\/\/fw02.zend.com\/issues\/rest\/api\/latest\/user?username=davidjmemmett",
                "name": "davidjmemmett",
                "displayName": "David JM Emmett",
                "active": true
            }
        },
        "created": {
            "name": "created",
            "type": "java.util.Date",
            "value": "2011-11-15T13:21:27.000+0000"
        },
        "updated": {
            "name": "updated",
            "type": "java.util.Date",
            "value": "2011-11-15T15:20:07.000+0000"
        },
        "customfield_10041": {
            "name": "Tags",
            "type": "com.atlassian.jira.plugin.system.customfieldtypes:labels",
            "value": [
                "S3",
                "Zend_Cloud_StorageService",
                "listItems"
            ]
        },
        "description": {
            "name": "description",
            "type": "java.lang.String",
            "value": "It is only possible to retrieve 1000 filepaths using Zend_Cloud_StorageService_Adapter_S3::listItems(), then the paths are returned in a different format to Zend_Cloud_StorageService_Adapter_FileSystem::listItems().\r\n\r\nZend_Cloud_StorageService_Adapter_FileSystem::listItems() returns an array of paths relative to it's first argument whereas Zend_Cloud_StorageService_Adapter_S3::listItems() returns an array of absolute paths relative to the root of the FS.\r\n\r\nCould we ensure that the filepaths returned are in the same (relative) format?"
        },
        "priority": {
            "name": "priority",
            "type": "com.atlassian.jira.issue.priority.Priority",
            "value": {
                "self": "http:\/\/fw02.zend.com\/issues\/rest\/api\/latest\/priority\/3",
                "name": "Major"
            }
        },
        "duedate": {
            "name": "duedate",
            "type": "java.util.Date"
        },
        "customfield_10022": {
            "name": "Fix Version Priority",
            "type": "com.atlassian.jira.plugin.system.customfieldtypes:select"
        },
        "watcher": {
            "name": "watcher",
            "type": "watcher",
            "value": {
                "self": "http:\/\/fw02.zend.com\/issues\/rest\/api\/latest\/issue\/ZF-11889\/watchers",
                "isWatching": false,
                "watchCount": 1
            }
        },
        "worklog": {
            "name": "worklog",
            "type": "worklog",
            "value": [

            ]
        },
        "status": {
            "name": "status",
            "type": "com.atlassian.jira.issue.status.Status",
            "value": {
                "self": "http:\/\/fw02.zend.com\/issues\/rest\/api\/latest\/status\/1",
                "name": "Open"
            }
        },
        "labels": {
            "name": "labels",
            "type": "com.atlassian.jira.issue.label.Label",
            "value": [
                "S3",
                "Zend_Cloud_StorageService",
                "listItems"
            ]
        },
        "assignee": {
            "name": "assignee",
            "type": "com.opensymphony.user.User",
            "value": {
                "self": "http:\/\/fw02.zend.com\/issues\/rest\/api\/latest\/user?username=zimuel",
                "name": "zimuel",
                "displayName": "Enrico Zimuel",
                "active": true
            }
        },
        "links": {
            "name": "links",
            "type": "issuelinks",
            "value": [

            ]
        },
        "attachment": {
            "name": "attachment",
            "type": "attachment",
            "value": [

            ]
        },
        "sub-tasks": {
            "name": "sub-tasks",
            "type": "issuelinks",
            "value": [

            ]
        },
        "versions": {
            "name": "versions",
            "type": "com.atlassian.jira.project.version.Version",
            "value": [
                {
                    "self": "http:\/\/fw02.zend.com\/issues\/rest\/api\/latest\/version\/10980",
                    "id": 10980,
                    "description": "Mini Release",
                    "name": "1.11.10",
                    "userReleaseDate": "04\/Aug\/11",
                    "archived": false,
                    "releaseDate": "2011-08-04",
                    "released": true
                }
            ]
        },
        "project": {
            "name": "project",
            "type": "com.atlassian.jira.project.Project",
            "value": {
                "self": "http:\/\/fw02.zend.com\/issues\/rest\/api\/latest\/project\/ZF",
                "key": "ZF",
                "name": "Zend Framework",
                "roles": {

                }
            }
        },
        "components": {
            "name": "components",
            "type": "com.atlassian.jira.bc.project.component.ProjectComponent",
            "value": [
                {
                    "self": "http:\/\/fw02.zend.com\/issues\/rest\/api\/latest\/component\/10502",
                    "id": 10502,
                    "name": "Zend_Cloud_StorageService",
                    "isAssigneeTypeValid": false
                }
            ]
        },
        "comment": {
            "name": "comment",
            "type": "com.atlassian.jira.issue.fields.CommentSystemField",
            "value": [
                {
                    "self": "http:\/\/fw02.zend.com\/issues\/rest\/api\/latest\/comment\/49100",
                    "author": {
                        "self": "http:\/\/fw02.zend.com\/issues\/rest\/api\/latest\/user?username=davidjmemmett",
                        "name": "davidjmemmett",
                        "displayName": "David JM Emmett",
                        "active": true
                    },
                    "body": "Not sure if this should be a separate issue or not, but the path passed into Zend_Cloud_StorageService_Adapter_S3::listItems() is also ignored. It should set the 'prefix' option for Zend_Service_Amazon_S3::getObjectsByBucket().",
                    "updateAuthor": {
                        "self": "http:\/\/fw02.zend.com\/issues\/rest\/api\/latest\/user?username=davidjmemmett",
                        "name": "davidjmemmett",
                        "displayName": "David JM Emmett",
                        "active": true
                    },
                    "created": "2011-11-15T13:24:36.000+0000",
                    "updated": "2011-11-15T13:24:36.000+0000"
                }
            ]
        }
    },
    "transitions": "http:\/\/fw02.zend.com\/issues\/rest\/api\/latest\/issue\/ZF-11889\/transitions"
}