{
    "expand": "html",
    "self": "http:\/\/fw02.zend.com\/issues\/rest\/api\/latest\/issue\/ZF-2073",
    "key": "ZF-2073",
    "fields": {
        "summary": {
            "name": "summary",
            "type": "java.lang.String",
            "value": "Zend_Filter_Digits doesn't work in multibyte languages."
        },
        "timetracking": {
            "name": "timetracking",
            "type": "com.atlassian.jira.issue.fields.TimeTrackingSystemField",
            "value": {
                "timeoriginalestimate": 1440,
                "timeestimate": 1440
            }
        },
        "issuetype": {
            "name": "issuetype",
            "type": "com.atlassian.jira.issue.issuetype.IssueType",
            "value": {
                "self": "http:\/\/fw02.zend.com\/issues\/rest\/api\/latest\/issueType\/4",
                "name": "Improvement",
                "subtask": false
            }
        },
        "votes": {
            "name": "votes",
            "type": "com.atlassian.jira.issue.fields.VotesSystemField",
            "value": {
                "self": "http:\/\/fw02.zend.com\/issues\/rest\/api\/latest\/issue\/ZF-2073\/votes",
                "votes": 1,
                "hasVoted": false
            }
        },
        "security": {
            "name": "security",
            "type": "com.atlassian.jira.issue.security.IssueSecurityLevel"
        },
        "resolution": {
            "name": "resolution",
            "type": "com.atlassian.jira.issue.resolution.Resolution",
            "value": {
                "self": "http:\/\/fw02.zend.com\/issues\/rest\/api\/latest\/resolution\/1",
                "name": "Fixed"
            }
        },
        "fixVersions": {
            "name": "fixVersions",
            "type": "com.atlassian.jira.project.version.Version",
            "value": [
                {
                    "self": "http:\/\/fw02.zend.com\/issues\/rest\/api\/latest\/version\/10172",
                    "id": 10172,
                    "description": "Minor Release",
                    "name": "1.5.0",
                    "userReleaseDate": "17\/Mar\/08",
                    "archived": true,
                    "releaseDate": "2008-03-17",
                    "released": true
                }
            ]
        },
        "resolutiondate": {
            "name": "resolutiondate",
            "type": "java.util.Date",
            "value": "2008-03-09T10:34:23.000+0000"
        },
        "reporter": {
            "name": "reporter",
            "type": "com.opensymphony.user.User",
            "value": {
                "self": "http:\/\/fw02.zend.com\/issues\/rest\/api\/latest\/user?username=yoshida@zend.co.jp",
                "name": "yoshida@zend.co.jp",
                "displayName": "old of Satoru Yoshida",
                "active": true
            }
        },
        "created": {
            "name": "created",
            "type": "java.util.Date",
            "value": "2007-10-16T03:30:50.000+0000"
        },
        "updated": {
            "name": "updated",
            "type": "java.util.Date",
            "value": "2011-08-03T14:26:40.000+0000"
        },
        "customfield_10041": {
            "name": "Tags",
            "type": "com.atlassian.jira.plugin.system.customfieldtypes:labels"
        },
        "description": {
            "name": "description",
            "type": "java.lang.String",
            "value": "Zend\/Filter\/Digits.php is not available in the multibyte languages.\r\nThe line 74 is written follow now.\r\n\r\n$pattern = '\/[\\p{^N}]\/';\r\n\r\nI propose to change as attachment."
        },
        "priority": {
            "name": "priority",
            "type": "com.atlassian.jira.issue.priority.Priority",
            "value": {
                "self": "http:\/\/fw02.zend.com\/issues\/rest\/api\/latest\/priority\/2",
                "name": "Critical"
            }
        },
        "duedate": {
            "name": "duedate",
            "type": "java.util.Date"
        },
        "customfield_10022": {
            "name": "Fix Version Priority",
            "type": "com.atlassian.jira.plugin.system.customfieldtypes:select",
            "value": {
                "self": "http:\/\/fw02.zend.com\/issues\/rest\/api\/latest\/customFieldOption\/10039",
                "value": "  Should Have"
            }
        },
        "watcher": {
            "name": "watcher",
            "type": "watcher",
            "value": {
                "self": "http:\/\/fw02.zend.com\/issues\/rest\/api\/latest\/issue\/ZF-2073\/watchers",
                "isWatching": false,
                "watchCount": 1
            }
        },
        "worklog": {
            "name": "worklog",
            "type": "worklog",
            "value": [

            ]
        },
        "status": {
            "name": "status",
            "type": "com.atlassian.jira.issue.status.Status",
            "value": {
                "self": "http:\/\/fw02.zend.com\/issues\/rest\/api\/latest\/status\/5",
                "name": "Resolved"
            }
        },
        "labels": {
            "name": "labels",
            "type": "com.atlassian.jira.issue.label.Label",
            "value": [

            ]
        },
        "assignee": {
            "name": "assignee",
            "type": "com.opensymphony.user.User",
            "value": {
                "self": "http:\/\/fw02.zend.com\/issues\/rest\/api\/latest\/user?username=satoruyoshida",
                "name": "satoruyoshida",
                "displayName": "Satoru Yoshida",
                "active": true
            }
        },
        "links": {
            "name": "links",
            "type": "issuelinks",
            "value": [
                {
                    "issueKey": "ZF-2107",
                    "issue": "http:\/\/fw02.zend.com\/issues\/rest\/api\/latest\/issue\/ZF-2107",
                    "type": {
                        "name": "Related",
                        "direction": "OUTBOUND",
                        "description": "is related to"
                    }
                },
                {
                    "issueKey": "ZF-2108",
                    "issue": "http:\/\/fw02.zend.com\/issues\/rest\/api\/latest\/issue\/ZF-2108",
                    "type": {
                        "name": "Related",
                        "direction": "INBOUND",
                        "description": "is related to"
                    }
                }
            ]
        },
        "attachment": {
            "name": "attachment",
            "type": "attachment",
            "value": [
                {
                    "self": "http:\/\/fw02.zend.com\/issues\/rest\/api\/latest\/attachment\/10937",
                    "filename": "zf_2073_20071127.txt",
                    "author": {
                        "self": "http:\/\/fw02.zend.com\/issues\/rest\/api\/latest\/user?username=yoshida@zend.co.jp",
                        "name": "yoshida@zend.co.jp",
                        "displayName": "old of Satoru Yoshida",
                        "active": true
                    },
                    "created": "2007-11-26T20:29:16.000+0000",
                    "size": 454,
                    "mimeType": "text\/plain",
                    "content": "http:\/\/fw02.zend.com\/issues\/secure\/attachment\/10937\/zf_2073_20071127.txt"
                },
                {
                    "self": "http:\/\/fw02.zend.com\/issues\/rest\/api\/latest\/attachment\/10938",
                    "filename": "ZF_2073_20071127testpattern.txt",
                    "author": {
                        "self": "http:\/\/fw02.zend.com\/issues\/rest\/api\/latest\/user?username=yoshida@zend.co.jp",
                        "name": "yoshida@zend.co.jp",
                        "displayName": "old of Satoru Yoshida",
                        "active": true
                    },
                    "created": "2007-11-27T00:07:08.000+0000",
                    "size": 540,
                    "mimeType": "text\/plain",
                    "content": "http:\/\/fw02.zend.com\/issues\/secure\/attachment\/10938\/ZF_2073_20071127testpattern.txt"
                }
            ]
        },
        "sub-tasks": {
            "name": "sub-tasks",
            "type": "issuelinks",
            "value": [

            ]
        },
        "versions": {
            "name": "versions",
            "type": "com.atlassian.jira.project.version.Version",
            "value": [
                {
                    "self": "http:\/\/fw02.zend.com\/issues\/rest\/api\/latest\/version\/10130",
                    "id": 10130,
                    "description": "Mini Release",
                    "name": "1.0.2",
                    "userReleaseDate": "25\/Sep\/07",
                    "archived": true,
                    "releaseDate": "2007-09-25",
                    "released": true
                }
            ]
        },
        "project": {
            "name": "project",
            "type": "com.atlassian.jira.project.Project",
            "value": {
                "self": "http:\/\/fw02.zend.com\/issues\/rest\/api\/latest\/project\/ZF",
                "key": "ZF",
                "name": "Zend Framework",
                "roles": {

                }
            }
        },
        "components": {
            "name": "components",
            "type": "com.atlassian.jira.bc.project.component.ProjectComponent",
            "value": [
                {
                    "self": "http:\/\/fw02.zend.com\/issues\/rest\/api\/latest\/component\/10013",
                    "id": 10013,
                    "name": "Zend_Filter",
                    "description": "methods for filtering data",
                    "isAssigneeTypeValid": false
                }
            ]
        },
        "comment": {
            "name": "comment",
            "type": "com.atlassian.jira.issue.fields.CommentSystemField",
            "value": [
                {
                    "self": "http:\/\/fw02.zend.com\/issues\/rest\/api\/latest\/comment\/17434",
                    "author": {
                        "self": "http:\/\/fw02.zend.com\/issues\/rest\/api\/latest\/user?username=darby",
                        "name": "darby",
                        "displayName": "Darby Felton",
                        "active": true
                    },
                    "body": "Perhaps you or someone else could contribute tests for {{Zend_Filter_DigitsTest}} ({{tests\/Zend\/Filter\/DigitsTest.php}}) that would cover the proposed functionality? Though I attempted such a test with [SVN r6765|http:\/\/framework.zend.com\/fisheye\/changelog\/Zend_Framework\/?cs=6765], I'm having some difficulty adding multibyte characters to the unit tests with my system.",
                    "updateAuthor": {
                        "self": "http:\/\/fw02.zend.com\/issues\/rest\/api\/latest\/user?username=darby",
                        "name": "darby",
                        "displayName": "Darby Felton",
                        "active": true
                    },
                    "created": "2007-11-07T12:11:45.000+0000",
                    "updated": "2007-11-07T12:11:45.000+0000"
                },
                {
                    "self": "http:\/\/fw02.zend.com\/issues\/rest\/api\/latest\/comment\/17435",
                    "author": {
                        "self": "http:\/\/fw02.zend.com\/issues\/rest\/api\/latest\/user?username=darby",
                        "name": "darby",
                        "displayName": "Darby Felton",
                        "active": true
                    },
                    "body": "Lowering priority to minor since an easy workaround (extend the class) is present.",
                    "updateAuthor": {
                        "self": "http:\/\/fw02.zend.com\/issues\/rest\/api\/latest\/user?username=darby",
                        "name": "darby",
                        "displayName": "Darby Felton",
                        "active": true
                    },
                    "created": "2007-11-07T12:12:29.000+0000",
                    "updated": "2007-11-07T12:12:29.000+0000"
                },
                {
                    "self": "http:\/\/fw02.zend.com\/issues\/rest\/api\/latest\/comment\/17707",
                    "author": {
                        "self": "http:\/\/fw02.zend.com\/issues\/rest\/api\/latest\/user?username=yoshida@zend.co.jp",
                        "name": "yoshida@zend.co.jp",
                        "displayName": "old of Satoru Yoshida",
                        "active": true
                    },
                    "body": "Sorry, My Description is harmful for in Zend_Validate_Ccnum. \nThe component depends on Zend_Filter_Digits.\n\nI want to cansel this Issue and SVN r6765.",
                    "updateAuthor": {
                        "self": "http:\/\/fw02.zend.com\/issues\/rest\/api\/latest\/user?username=yoshida@zend.co.jp",
                        "name": "yoshida@zend.co.jp",
                        "displayName": "old of Satoru Yoshida",
                        "active": true
                    },
                    "created": "2007-11-26T03:49:02.000+0000",
                    "updated": "2007-11-26T03:49:02.000+0000"
                },
                {
                    "self": "http:\/\/fw02.zend.com\/issues\/rest\/api\/latest\/comment\/17722",
                    "author": {
                        "self": "http:\/\/fw02.zend.com\/issues\/rest\/api\/latest\/user?username=yoshida@zend.co.jp",
                        "name": "yoshida@zend.co.jp",
                        "displayName": "old of Satoru Yoshida",
                        "active": true
                    },
                    "body": "I find a plan.",
                    "updateAuthor": {
                        "self": "http:\/\/fw02.zend.com\/issues\/rest\/api\/latest\/user?username=yoshida@zend.co.jp",
                        "name": "yoshida@zend.co.jp",
                        "displayName": "old of Satoru Yoshida",
                        "active": true
                    },
                    "created": "2007-11-26T20:29:16.000+0000",
                    "updated": "2007-11-26T20:29:16.000+0000"
                },
                {
                    "self": "http:\/\/fw02.zend.com\/issues\/rest\/api\/latest\/comment\/17724",
                    "author": {
                        "self": "http:\/\/fw02.zend.com\/issues\/rest\/api\/latest\/user?username=yoshida@zend.co.jp",
                        "name": "yoshida@zend.co.jp",
                        "displayName": "old of Satoru Yoshida",
                        "active": true
                    },
                    "body": "I make test pattern for Zend_Filter_DigitsTest.php .  I hope this will be useful.",
                    "updateAuthor": {
                        "self": "http:\/\/fw02.zend.com\/issues\/rest\/api\/latest\/user?username=yoshida@zend.co.jp",
                        "name": "yoshida@zend.co.jp",
                        "displayName": "old of Satoru Yoshida",
                        "active": true
                    },
                    "created": "2007-11-27T00:07:08.000+0000",
                    "updated": "2007-11-27T00:07:08.000+0000"
                },
                {
                    "self": "http:\/\/fw02.zend.com\/issues\/rest\/api\/latest\/comment\/17933",
                    "author": {
                        "self": "http:\/\/fw02.zend.com\/issues\/rest\/api\/latest\/user?username=wil",
                        "name": "wil",
                        "displayName": "Wil Sinclair",
                        "active": true
                    },
                    "body": "What is the status of this issue? Do we have a fix? Is it checked in? Satoru, if you have a fix, I can assign this to you and you can close it.",
                    "updateAuthor": {
                        "self": "http:\/\/fw02.zend.com\/issues\/rest\/api\/latest\/user?username=wil",
                        "name": "wil",
                        "displayName": "Wil Sinclair",
                        "active": true
                    },
                    "created": "2007-12-14T17:02:41.000+0000",
                    "updated": "2007-12-14T17:02:41.000+0000"
                },
                {
                    "self": "http:\/\/fw02.zend.com\/issues\/rest\/api\/latest\/comment\/17967",
                    "author": {
                        "self": "http:\/\/fw02.zend.com\/issues\/rest\/api\/latest\/user?username=yoshida@zend.co.jp",
                        "name": "yoshida@zend.co.jp",
                        "displayName": "old of Satoru Yoshida",
                        "active": true
                    },
                    "body": "I offered a solution in the file attachments, but it does not be discussed or applied as same as ZF-2107 and ZF-2108.\nYes I have an idea to fix. But how to edit  Zend\/Filter\/Digits.php and Zend\/Filter\/DigitsTest.php?",
                    "updateAuthor": {
                        "self": "http:\/\/fw02.zend.com\/issues\/rest\/api\/latest\/user?username=yoshida@zend.co.jp",
                        "name": "yoshida@zend.co.jp",
                        "displayName": "old of Satoru Yoshida",
                        "active": true
                    },
                    "created": "2007-12-17T00:26:04.000+0000",
                    "updated": "2007-12-17T00:26:04.000+0000"
                },
                {
                    "self": "http:\/\/fw02.zend.com\/issues\/rest\/api\/latest\/comment\/18647",
                    "author": {
                        "self": "http:\/\/fw02.zend.com\/issues\/rest\/api\/latest\/user?username=darby",
                        "name": "darby",
                        "displayName": "Darby Felton",
                        "active": true
                    },
                    "body": "Assigning to [~yoshida@zend.co.jp]. Please contact me directly when you are ready to commit your changes, and I'll take care of giving you SVN credentials (e.g., username and password) needed to commit successfully. Thank you! :)",
                    "updateAuthor": {
                        "self": "http:\/\/fw02.zend.com\/issues\/rest\/api\/latest\/user?username=darby",
                        "name": "darby",
                        "displayName": "Darby Felton",
                        "active": true
                    },
                    "created": "2008-01-29T09:51:01.000+0000",
                    "updated": "2008-01-29T09:51:01.000+0000"
                },
                {
                    "self": "http:\/\/fw02.zend.com\/issues\/rest\/api\/latest\/comment\/19775",
                    "author": {
                        "self": "http:\/\/fw02.zend.com\/issues\/rest\/api\/latest\/user?username=yoshida@zend.co.jp",
                        "name": "yoshida@zend.co.jp",
                        "displayName": "old of Satoru Yoshida",
                        "active": true
                    },
                    "body": "Resolved in SVN r8710",
                    "updateAuthor": {
                        "self": "http:\/\/fw02.zend.com\/issues\/rest\/api\/latest\/user?username=yoshida@zend.co.jp",
                        "name": "yoshida@zend.co.jp",
                        "displayName": "old of Satoru Yoshida",
                        "active": true
                    },
                    "created": "2008-03-09T10:34:23.000+0000",
                    "updated": "2008-03-09T10:34:23.000+0000"
                }
            ]
        }
    },
    "transitions": "http:\/\/fw02.zend.com\/issues\/rest\/api\/latest\/issue\/ZF-2073\/transitions"
}